{
    "transcript": [
        {
            "speaker": "SPEAKER_00",
            "start": 0.21,
            "end": 1.53,
            "text": "Here you go, boys. I'll pick it up when you're ready."
        },
        {
            "speaker": "SPEAKER_01",
            "start": 2.94,
            "end": 3.68,
            "text": "Thanks for dinner, buddy."
        },
        {
            "speaker": "SPEAKER_01",
            "start": 4.22,
            "end": 5.14,
            "text": "Yeah, real big of you."
        },
        {
            "speaker": "SPEAKER_01",
            "start": 5.9,
            "end": 6.68,
            "text": "Hurry, hurry, hurry."
        },
        {
            "speaker": "SPEAKER_00",
            "start": 8.84,
            "end": 10.9,
            "text": "Oh, and don't cheap out on the tip. We all know you're loaded now."
        }
    ],
    "summary": ""
}